feeder/__init__.py
feeder/cli.py
feeder/feeder.py
json_feeder-0.1.1.dist-info/METADATA
json_feeder-0.1.1.dist-info/WHEEL
json_feeder-0.1.1.dist-info/entry_points.txt
json_feeder-0.1.1.dist-info/top_level.txt
json_feeder-0.1.1.dist-info/RECORD
