Metadata-Version: 2.1
Name: json-feeder
Version: 0.1.1
Summary: A framework for generate JSON feeds
Home-page: https://github.com/sesh/feeder
Author: Brenton Cleeland
License: MIT License
Project-URL: Issues, https://github.com/sesh/feeder/issues
Project-URL: CI, https://github.com/sesh/feeder/actions
Project-URL: Changelog, https://github.com/sesh/feeder/releases
Requires-Python: >=3.8
Requires-Dist: thttp
